fxconverter/__init__.py
fxconverter/__version__.py
fxconverter/cache.py
fxconverter/converter.py
fxconverter/exceptions.py
fxconverter/providers/__init__.py
fxconverter/providers/base.py
fxconverter/providers/exchangerate_api.py
fxconverter-1.0.1.dist-info/licenses/LICENSE
fxconverter-1.0.1.dist-info/METADATA
fxconverter-1.0.1.dist-info/WHEEL
fxconverter-1.0.1.dist-info/top_level.txt
fxconverter-1.0.1.dist-info/RECORD
