Metadata-Version: 2.4
Name: fxconverter
Version: 1.0.1
Summary: A modern, production-ready currency converter with live exchange rates
Author-email: NtohnwiBih <mforbesintohnwi@gmail.com>
License: MIT
Project-URL: Homepage, https://github.com/NtohnwiBih/fxconverter
Project-URL: Documentation, https://github.com/NtohnwiBih/fxconverter#readme
Project-URL: Repository, https://github.com/NtohnwiBih/fxconverter
Project-URL: Bug Tracker, https://github.com/NtohnwiBih/fxconverter/issues
Keywords: currency,converter,exchange,rates,forex,finance
Classifier: Development Status :: 5 - Production/Stable
Classifier: Intended Audience :: Developers
Classifier: License :: OSI Approved :: MIT License
Classifier: Programming Language :: Python :: 3
Classifier: Programming Language :: Python :: 3.8
Classifier: Programming Language :: Python :: 3.9
Classifier: Programming Language :: Python :: 3.10
Classifier: Programming Language :: Python :: 3.11
Classifier: Programming Language :: Python :: 3.12
Classifier: Topic :: Software Development :: Libraries :: Python Modules
Classifier: Topic :: Office/Business :: Financial
Requires-Python: >=3.8
License-File: LICENSE
Requires-Dist: requests>=2.25.0
Provides-Extra: dev
Requires-Dist: pytest>=7.0.0; extra == "dev"
Requires-Dist: pytest-cov>=4.0.0; extra == "dev"
Requires-Dist: black>=23.0.0; extra == "dev"
Requires-Dist: flake8>=6.0.0; extra == "dev"
Requires-Dist: mypy>=1.0.0; extra == "dev"
Requires-Dist: build>=0.10.0; extra == "dev"
Requires-Dist: twine>=4.0.0; extra == "dev"
Dynamic: license-file
Dynamic: requires-python
